html2docxconverter-0.1.8.dist-info/licenses/LICENSE
htmltodocx/__init__.py
htmltodocx/colors.py
htmltodocx/config.py
htmltodocx/htmlimage.py
htmltodocx/htmllist.py
htmltodocx/htmltable.py
htmltodocx/htmltodocx.py
htmltodocx/parse_style.py
htmltodocx/schemas.py
html2docxconverter-0.1.8.dist-info/METADATA
html2docxconverter-0.1.8.dist-info/WHEEL
html2docxconverter-0.1.8.dist-info/top_level.txt
html2docxconverter-0.1.8.dist-info/RECORD
