Metadata-Version: 2.4
Name: html2docxconverter
Version: 0.1.8
Summary: Конвертирует HTML в DOCX с сохранением стилей: списков, таблиц, шрифтов, цветов и т.д.
Author: pew
License: MIT
Project-URL: Homepage, https://github.com/Dnnbg123/html2docxconverter
Project-URL: Repository, https://github.com/Dnnbg123/html2docxconverter
Project-URL: Bug_Tracker, https://github.com/Dnnbg123/html2docxconverter/issues
Keywords: html,docx,word,convert,parser
Classifier: Programming Language :: Python :: 3
Classifier: License :: OSI Approved :: MIT License
Classifier: Operating System :: OS Independent
Requires-Python: >=3.11
License-File: LICENSE
Requires-Dist: python-docx<1.3,>=1.2.0
Requires-Dist: beautifulsoup4>=4.14.3
Requires-Dist: soupsieve>=2.8.1
Requires-Dist: requests>=2.32.5
Requires-Dist: pillow>=12.1.0
Dynamic: license-file
